{
  "type": "Feature",
  "geometry": {
    "type": "Polygon",
    "coordinates": [
      [
        [-75.992431640625, -22.690052257634008],
        [-75.8221435546875, -22.69512018496569],
        [-75.8331298828125, -22.781246241104398],
        [-75.596923828125, -22.847070687839064],
        [-75.3607177734375, -23.05446192669382],
        [-75.772705078125, -23.46324633155035],
        [-76.13525390625, -23.468285200853245],
        [-75.87158203125, -22.968509022673913],
        [-76.09130859375, -22.79643932091949],
        [-75.992431640625, -22.690052257634008]
      ]
    ]
  },
  "properties": {
    "STATEFP": "42",
    "CD119FP": "06",
    "GEOID": "4206",
    "GEOIDFQ": "5001900US4206",
    "NAMELSAD": "Congressional District 6",
    "LSAD": "C2",
    "CDSESSN": "119",
    "MTFCC": "G5200",
    "FUNCSTAT": "N",
    "ALAND": 2395755266,
    "AWATER": 27816359,
    "INTPTLAT": "+40.0269229",
    "INTPTLON": "-075.7766366",
    "id": "42-06",
    "state_fips": "42",
    "state_name": "Pennsylvania",
    "state_abbr": "PA",
    "district_num": "06",
    "name": "PA-06",
    "full_name": "Pennsylvania Congressional District 06",
    "geoid": "4206"
  }
}
